README
setup.py
webpy_mongodb_sessions/__init__.py
webpy_mongodb_sessions/session.py
webpy_mongodb_sessions/users.py
webpy_mongodb_sessions.egg-info/PKG-INFO
webpy_mongodb_sessions.egg-info/SOURCES.txt
webpy_mongodb_sessions.egg-info/dependency_links.txt
webpy_mongodb_sessions.egg-info/requires.txt
webpy_mongodb_sessions.egg-info/top_level.txt