Metadata-Version: 1.0
Name: webpy-mongodb-sessions
Version: 0.1
Summary: Implements a MongoDB-backed session store for web.py
Home-page: http://pypi.python.org/pypi/webpy-mongodb-sessions
Author: Steven Anderson
Author-email: steve@whilefalse.net
License: MIT
Keywords: web.py mongodb
Platform: UNKNOWN
